{"log2_no_instances": 6.643856189774724, "log2_no_attributes": 1.0, "log10_no_instances": 4.605170185988092, "log10_no_attributes": 0.6931471805599453, "instances_to_features": 50.0, "log_instances_to_features": 3.912023005428146, "features_to_instances": 50.0, "log_features_to_instances": 3.912023005428146, "Hopkin's statistic": 0.8419377749020377, "pct_of_discrete_attributes": 0.0, "mean_entropy_of_discrete_attributes": 0, "mean_absolute_correlation_of_continuous_attributes": 0.16070921528425297, "mean_concentration_of_discrete_attributes": NaN, "pca_95_components_to_features_ratio": 1.0, "pca_first_component_skewness": 0.0, "pca_first_component_kurtosis": -2.0, "pct_of_outliers": 0.01, "pct_of_mv": 0.0, "min_skewness_of_continuous_attributes": -0.31174576056215275, "max_skewness_of_continuous_attributes": 0.5558307335748922, "mean_skewness_of_continuous_attributes": 0.12204248650636973, "std_skewness_of_continuous_attributes": 0.4337882470685225, "min_kurtosis_of_continuous_attributes": -0.31174576056215275, "max_kurtosis_of_continuous_attributes": 0.5558307335748922, "mean_kurtosis_of_continuous_attributes": 0.12204248650636973, "std_kurtosis_of_continuous_attributes": 0.4337882470685225, "t_squared_mv_normality": 0.43, "t_squared_skewness": 1.493736567629202, "t_squared_outliers": 0.01, "meanshift_silhouette": 0.733730183739091, "meanshift_dunn": 0.42746716515625044, "meanshift_cindex": 0.003699203525279682, "meanshift_calinski_harabasz": 489.8545855072555, "meanshift_davies_bouldin": 0.36384903801598895, "meanshift_sdbw": 0.1223597503611324, "meanshift_cdbw": null, "meanshift_tau": -8.077795209579994e-08, "meanshift_ratkowsky_lance": 0.4897736477775578, "meanshift_mcclain_rao": 0.2668954917063196, "DBSCAN_silhouette": 0.17119063678927698, "DBSCAN_davies_bouldin": 1.5312540053675714, "DBSCAN_calinski_harabasz": 26.671888740523215, "OPTICS_silhouette": -0.0371271702942473, "OPTICS_davies_bouldin": 1.851755550675263, "OPTICS_calinski_harabasz": 15.195613841181354, "ferrari_distance_based": {"Mean": 3.801704674050102, "Variance": 6.522211491861906, "Standard deviation": 2.5538620737741313, "Skewness": 0.3222008856905913, "Kurtosis": -1.2985523378077206, "% of values in [0, 0.1]": 0.0018181818181818182, "% of values in [0.1, 0.2]": 0.005050505050505051, "% of values in [0.2, 0.3]": 0.007676767676767677, "% of values in [0.3, 0.4]": 0.009696969696969697, "% of values in [0.4, 0.5]": 0.012323232323232323, "% of values in [0.5, 0.6]": 0.013737373737373737, "% of values in [0.6, 0.7]": 0.016363636363636365, "% of values in [0.7, 0.8]": 0.01696969696969697, "% of values in [0.8, 0.9]": 0.025252525252525252, "% of values in [0.9, 1]": 0.023636363636363636, "% of values with |Z-score| in [0,1)": 0.23555555555555555, "% of values with |Z-score| in [1,2)": 0.2109090909090909, "% of values with |Z-score| in [2,3)": 0.010505050505050505, "% of values with |Z-score| in [3, infinity)": 0.0}, "correlation_based": {"Mean": NaN, "Variance": NaN, "Standard deviation": NaN, "Skewness": NaN, "Kurtosis": NaN, "% of values in [0, 0.1]": 0.49454545454545457, "% of values in [0.1, 0.2]": 0.0, "% of values in [0.2, 0.3]": 0.0, "% of values in [0.3, 0.4]": 0.0, "% of values in [0.4, 0.5]": 0.0, "% of values in [0.5, 0.6]": 0.0, "% of values in [0.6, 0.7]": 0.0, "% of values in [0.7, 0.8]": 0.0, "% of values in [0.8, 0.9]": 0.0, "% of values in [0.9, 1]": 0.48545454545454547, "% of values with |Z-score| in [0,1)": 0.0, "% of values with |Z-score| in [1,2)": 0.0, "% of values with |Z-score| in [2,3)": 0.0, "% of values with |Z-score| in [3, infinity)": 0.0}, "correlation_and_distance": {"Mean": NaN, "Variance": NaN, "Standard deviation": NaN, "Skewness": NaN, "Kurtosis": NaN, "% of values in [0, 0.1]": 0.10525252525252525, "% of values in [0.1, 0.2]": 0.14262626262626263, "% of values in [0.2, 0.3]": 0.18606060606060607, "% of values in [0.3, 0.4]": 0.1195959595959596, "% of values in [0.4, 0.5]": 0.10868686868686869, "% of values in [0.5, 0.6]": 0.11898989898989899, "% of values in [0.6, 0.7]": 0.11898989898989899, "% of values in [0.7, 0.8]": 0.06222222222222222, "% of values in [0.8, 0.9]": 0.01575757575757576, "% of values in [0.9, 1]": 0.0018181818181818182, "% of values with |Z-score| in [0,1)": 0.0, "% of values with |Z-score| in [1,2)": 0.0, "% of values with |Z-score| in [2,3)": 0.0, "% of values with |Z-score| in [3, infinity)": 0.0}, "marcoge": {"marcoge_mf_1": 2.300750732421875, "marcoge_mf_2": 0.0, "marcoge_mf_3": 0.0, "marcoge_mf_4": 1.322924017906189, "marcoge_mf_5": 0.0, "marcoge_mf_6": 0.0, "marcoge_mf_7": 0.0, "marcoge_mf_8": 0.0, "marcoge_mf_9": 0.0, "marcoge_mf_10": 0.0, "marcoge_mf_11": 0.0, "marcoge_mf_12": 0.0, "marcoge_mf_13": 0.0, "marcoge_mf_14": 2.630197763442993, "marcoge_mf_15": 0.020107552409172058, "marcoge_mf_16": 1.8577498197555542, "marcoge_mf_17": 0.0, "marcoge_mf_18": 0.0, "marcoge_mf_19": 2.732825994491577, "marcoge_mf_20": 1.1301807165145874, "marcoge_mf_21": 0.0, "marcoge_mf_22": 0.0, "marcoge_mf_23": 0.0, "marcoge_mf_24": 2.2353250980377197, "marcoge_mf_25": 0.0, "marcoge_mf_26": 0.2862262427806854, "marcoge_mf_27": 0.0, "marcoge_mf_28": 0.0, "marcoge_mf_29": 2.1169931888580322, "marcoge_mf_30": 0.0538051500916481, "marcoge_mf_31": 0.0, "marcoge_mf_32": 0.0, "marcoge_mf_33": 0.0, "marcoge_mf_34": 1.1156408786773682, "marcoge_mf_35": 0.0, "marcoge_mf_36": 0.0, "marcoge_mf_37": 0.0, "marcoge_mf_38": 1.913732647895813, "marcoge_mf_39": 0.0, "marcoge_mf_40": 0.7086065411567688, "marcoge_mf_41": 0.0, "marcoge_mf_42": 0.0, "marcoge_mf_43": 0.0, "marcoge_mf_44": 0.0, "marcoge_mf_45": 0.0, "marcoge_mf_46": 0.0, "marcoge_mf_47": 0.0, "marcoge_mf_48": 0.0, "marcoge_mf_49": 2.219597578048706, "marcoge_mf_50": 0.0, "marcoge_mf_51": 0.0, "marcoge_mf_52": 0.0, "marcoge_mf_53": 0.0, "marcoge_mf_54": 0.0, "marcoge_mf_55": 0.0, "marcoge_mf_56": 1.4605932235717773, "marcoge_mf_57": 0.0, "marcoge_mf_58": 0.0, "marcoge_mf_59": 0.0, "marcoge_mf_60": 0.0, "marcoge_mf_61": 0.0, "marcoge_mf_62": 0.0, "marcoge_mf_63": 1.3607274293899536, "marcoge_mf_64": 0.0, "marcoge_mf_65": 0.0, "marcoge_mf_66": 0.767930269241333, "marcoge_mf_67": 0.0, "marcoge_mf_68": 2.0612471103668213, "marcoge_mf_69": 1.0592459440231323, "marcoge_mf_70": 0.0, "marcoge_mf_71": 0.9355882406234741, "marcoge_mf_72": 2.437432050704956, "marcoge_mf_73": 0.0, "marcoge_mf_74": 0.0, "marcoge_mf_75": 0.0, "marcoge_mf_76": 0.0, "marcoge_mf_77": 0.0, "marcoge_mf_78": 1.1985570192337036, "marcoge_mf_79": 1.9648878574371338, "marcoge_mf_80": 0.0, "marcoge_mf_81": 1.5136642456054688, "marcoge_mf_82": 0.0, "marcoge_mf_83": 1.4190717935562134, "marcoge_mf_84": 0.0, "marcoge_mf_85": 0.0, "marcoge_mf_86": 0.0, "marcoge_mf_87": 0.0, "marcoge_mf_88": 0.0, "marcoge_mf_89": 0.0, "marcoge_mf_90": 0.2577105164527893, "marcoge_mf_91": 1.241650104522705, "marcoge_mf_92": 0.0, "marcoge_mf_93": 0.0, "marcoge_mf_94": 2.133544445037842, "marcoge_mf_95": 0.3108975291252136, "marcoge_mf_96": 0.0, "marcoge_mf_97": 0.0, "marcoge_mf_98": 0.0, "marcoge_mf_99": 0.0, "marcoge_mf_100": 0.0, "marcoge_mf_101": 0.0, "marcoge_mf_102": 0.0, "marcoge_mf_103": 0.0, "marcoge_mf_104": 1.5658445358276367, "marcoge_mf_105": 2.6078031063079834, "marcoge_mf_106": 2.686431646347046, "marcoge_mf_107": 0.0, "marcoge_mf_108": 1.4426274299621582, "marcoge_mf_109": 0.9607281684875488, "marcoge_mf_110": 1.7846750020980835, "marcoge_mf_111": 0.0, "marcoge_mf_112": 0.0, "marcoge_mf_113": 0.8968563079833984, "marcoge_mf_114": 0.45465704798698425, "marcoge_mf_115": 0.0, "marcoge_mf_116": 1.177139163017273, "marcoge_mf_117": 1.1238144636154175, "marcoge_mf_118": 0.0, "marcoge_mf_119": 1.1317329406738281, "marcoge_mf_120": 0.0, "marcoge_mf_121": 2.1419196128845215, "marcoge_mf_122": 0.0, "marcoge_mf_123": 1.1676143407821655, "marcoge_mf_124": 0.0, "marcoge_mf_125": 1.3674753904342651, "marcoge_mf_126": 0.0, "marcoge_mf_127": 0.07494595646858215, "marcoge_mf_128": 1.2152988910675049, "marcoge_mf_129": 2.154313325881958, "marcoge_mf_130": 1.6819645166397095, "marcoge_mf_131": 0.0, "marcoge_mf_132": 0.0, "marcoge_mf_133": 0.0, "marcoge_mf_134": 0.5895126461982727, "marcoge_mf_135": 1.9321926832199097, "marcoge_mf_136": 1.1816362142562866, "marcoge_mf_137": 0.28712594509124756, "marcoge_mf_138": 1.2560796737670898, "marcoge_mf_139": 0.0, "marcoge_mf_140": 2.192995071411133, "marcoge_mf_141": 2.4685075283050537, "marcoge_mf_142": 0.8224565386772156, "marcoge_mf_143": 0.0, "marcoge_mf_144": 0.0, "marcoge_mf_145": 0.0, "marcoge_mf_146": 0.0, "marcoge_mf_147": 1.678840160369873, "marcoge_mf_148": 0.0, "marcoge_mf_149": 1.3369362354278564, "marcoge_mf_150": 0.0, "marcoge_mf_151": 0.0, "marcoge_mf_152": 0.0, "marcoge_mf_153": 0.0, "marcoge_mf_154": 0.7217738628387451, "marcoge_mf_155": 0.0, "marcoge_mf_156": 1.6774330139160156, "marcoge_mf_157": 0.0, "marcoge_mf_158": 1.0784224271774292, "marcoge_mf_159": 1.4422667026519775, "marcoge_mf_160": 0.0, "marcoge_mf_161": 0.0, "marcoge_mf_162": 0.0, "marcoge_mf_163": 0.0, "marcoge_mf_164": 0.0, "marcoge_mf_165": 0.0, "marcoge_mf_166": 0.0, "marcoge_mf_167": 0.0, "marcoge_mf_168": 0.0, "marcoge_mf_169": 0.0, "marcoge_mf_170": 1.1507846117019653, "marcoge_mf_171": 0.0, "marcoge_mf_172": 0.4386735260486603, "marcoge_mf_173": 0.0, "marcoge_mf_174": 1.000809907913208, "marcoge_mf_175": 0.0, "marcoge_mf_176": 0.0, "marcoge_mf_177": 0.0, "marcoge_mf_178": 0.0, "marcoge_mf_179": 0.0, "marcoge_mf_180": 0.0, "marcoge_mf_181": 0.0, "marcoge_mf_182": 0.0, "marcoge_mf_183": 0.0, "marcoge_mf_184": 0.0, "marcoge_mf_185": 0.0, "marcoge_mf_186": 1.4587420225143433, "marcoge_mf_187": 0.0, "marcoge_mf_188": 0.38850343227386475, "marcoge_mf_189": 0.0, "marcoge_mf_190": 0.41248318552970886, "marcoge_mf_191": 0.4300808310508728, "marcoge_mf_192": 0.0, "marcoge_mf_193": 0.0, "marcoge_mf_194": 0.0, "marcoge_mf_195": 2.267488718032837, "marcoge_mf_196": 0.0, "marcoge_mf_197": 0.0, "marcoge_mf_198": 1.2392557859420776, "marcoge_mf_199": 2.705754041671753, "marcoge_mf_200": 0.0, "marcoge_mf_201": 1.7435535192489624, "marcoge_mf_202": 0.0, "marcoge_mf_203": 0.0, "marcoge_mf_204": 0.0, "marcoge_mf_205": 0.452820360660553, "marcoge_mf_206": 0.0, "marcoge_mf_207": 0.0, "marcoge_mf_208": 0.0, "marcoge_mf_209": 0.0, "marcoge_mf_210": 0.681093692779541, "marcoge_mf_211": 0.09000886231660843, "marcoge_mf_212": 0.0, "marcoge_mf_213": 0.0, "marcoge_mf_214": 1.599036693572998, "marcoge_mf_215": 1.6134451627731323, "marcoge_mf_216": 1.1055340766906738, "marcoge_mf_217": 0.0, "marcoge_mf_218": 2.336900234222412, "marcoge_mf_219": 0.0, "marcoge_mf_220": 1.9122432470321655, "marcoge_mf_221": 1.7287864685058594, "marcoge_mf_222": 0.0, "marcoge_mf_223": 0.0, "marcoge_mf_224": 0.0, "marcoge_mf_225": 0.0, "marcoge_mf_226": 1.805017352104187, "marcoge_mf_227": 0.0, "marcoge_mf_228": 0.0, "marcoge_mf_229": 0.0, "marcoge_mf_230": 0.0, "marcoge_mf_231": 2.3690097332000732, "marcoge_mf_232": 1.2408387660980225, "marcoge_mf_233": 2.751084327697754, "marcoge_mf_234": 0.0, "marcoge_mf_235": 0.0, "marcoge_mf_236": 1.8340414762496948, "marcoge_mf_237": 0.0, "marcoge_mf_238": 0.0, "marcoge_mf_239": 0.0, "marcoge_mf_240": 2.1211605072021484, "marcoge_mf_241": 0.0, "marcoge_mf_242": 1.1164790391921997, "marcoge_mf_243": 2.2434723377227783, "marcoge_mf_244": 0.24865081906318665, "marcoge_mf_245": 0.0, "marcoge_mf_246": 1.0330251455307007, "marcoge_mf_247": 0.0, "marcoge_mf_248": 0.0, "marcoge_mf_249": 0.46050411462783813, "marcoge_mf_250": 0.6723046898841858, "marcoge_mf_251": 0.0, "marcoge_mf_252": 0.0, "marcoge_mf_253": 0.0, "marcoge_mf_254": 0.0, "marcoge_mf_255": 0.0, "marcoge_mf_256": 0.0, "marcoge_mf_257": 0.0, "marcoge_mf_258": 0.8337691426277161, "marcoge_mf_259": 0.0, "marcoge_mf_260": 0.0, "marcoge_mf_261": 0.0, "marcoge_mf_262": 0.0, "marcoge_mf_263": 0.0, "marcoge_mf_264": 1.2446210384368896, "marcoge_mf_265": 1.825011134147644, "marcoge_mf_266": 0.0, "marcoge_mf_267": 0.0, "marcoge_mf_268": 1.1048636436462402, "marcoge_mf_269": 1.1349576711654663, "marcoge_mf_270": 0.0, "marcoge_mf_271": 0.0, "marcoge_mf_272": 0.5626547932624817, "marcoge_mf_273": 0.0, "marcoge_mf_274": 0.0, "marcoge_mf_275": 0.0, "marcoge_mf_276": 1.7389620542526245, "marcoge_mf_277": 1.938175916671753, "marcoge_mf_278": 0.0, "marcoge_mf_279": 1.296397089958191, "marcoge_mf_280": 0.0, "marcoge_mf_281": 0.4817808270454407, "marcoge_mf_282": 0.0, "marcoge_mf_283": 0.0, "marcoge_mf_284": 0.0, "marcoge_mf_285": 1.522289752960205, "marcoge_mf_286": 0.0, "marcoge_mf_287": 0.0, "marcoge_mf_288": 0.0, "marcoge_mf_289": 0.0, "marcoge_mf_290": 0.990720808506012, "marcoge_mf_291": 0.0, "marcoge_mf_292": 0.0, "marcoge_mf_293": 0.0, "marcoge_mf_294": 1.9669864177703857, "marcoge_mf_295": 1.9877934455871582, "marcoge_mf_296": 2.014803171157837, "marcoge_mf_297": 0.0, "marcoge_mf_298": 0.0, "marcoge_mf_299": 0.0, "marcoge_mf_300": 0.0}}